Workbook

Sheet Parâmetros
A1: E2.7 — PARÂMETROS DO MODELO
A2: Equipe D — Ciclo 2. Texto azul sobre fundo amarelo = valor digitado (edite aqui). Todas as demais abas são fórmulas.
B4: Parâmetro | C4: Valor | D4: Unidade | E4: Fonte | F4: Situação
B5: Registros de frequência por mês | C5: 204 | D5: registros | E5: E1.7, aba 1, célula C9 (2.239 registros válidos em 11 meses) | F5: Declarado pela equipe no E1.7
B6: Tempo para registrar uma chamada em papel | C6: 6 | D6: min | E6: E1.7, aba 1, C10 (indicado como cronometrado na sessão) | F6: Cronometrado na sessão
B7: Tempo para transcrever a chamada para a planilha | C7: 9 | D7: min | E7: E1.7, aba 1, C11 | F7: Cronometrado na sessão
B8: Consultas a histórico por mês | C8: 35 | D8: consultas | E8: E1.7, aba 1, C13 (estimativa da coordenação) | F8: Estimativa
B9: Tempo para localizar um histórico | C9: 14 | D9: min | E9: E1.7, aba 1, C12 | F9: Cronometrado na sessão
B10: Horas semanais de consolidação (transferir registros para a planilha) | C10: 12 | D10: h/semana | E10: E1.2 (objetivo de reduzir de 12 h para até 3 h) e E1.7, aba 1, nota da C14 | F10: Documentado
B11: Semanas por mês | C11: 4 | D11: semanas | E11: E1.7, aba 1, nota da C14 (12 h x 4 semanas) | F11: Convenção do E1.7
B12: Dias de soma de presença por trimestre | C12: 3 | D12: dias | E12: Dossiê §3 (Marlene: "três dias por trimestre somando presença") | F12: Documentado
B13: Horas de trabalho por dia nessa tarefa | C13: 8 | D13: h/dia | E13: E1.7, aba 1, nota da C14 | F13: Convenção do E1.7
B14: Meses por trimestre | C14: 3 | D14: meses | E14: Calendário | F14: Fato
B15: Custo-hora médio da equipe do Instituto | C15: 18.5 | D15: R$/h | E15: E1.7, aba 3, C4 (estimativa a partir do salário informado pela coordenação) | F15: A confirmar: não há o salário em nenhum documento
B16: Retrabalho por informação perdida ou duplicada | C16: 320 | D16: R$/mês | E16: E1.7, aba 3, C9 | F16: Estimativa do E1.7
... B31: Eficácia máxima da solução (limite de p quando h cresce) | C31: 0.8 | D31: fração | E31: Premissa desta análise. Fica acima dos 75% de redução que a coordenação deseja na consolidação (E1.2: de 12 h para até 3 h) | F31: PREMISSA a confirmar

Sheet Modelo ajustado
A1: E2.7 — MODELO DE CUSTO AJUSTADO AOS DADOS
A2: Ajuste: as 48 h mensais de consolidação do E1.7 passam a ser separadas em transcrição (variável) e demais tarefas (fixas), o que elimina a dupla contagem.
B4: Componente | C4: Valor | D4: Unidade | E4: Como é calculado
B5: Consolidação mensal informada (12 h/semana x 4 semanas) | C5: =Parâmetros!$C$10*Parâmetros!$C$11 -> 48 | D5: h/mês | E5: 12 h por semana x 4 semanas
B6: Transcrição (variável com os registros) | C6: =Parâmetros!$C$5*Parâmetros!$C$7/60 -> 30.6 | D6: h/mês | E6: registros/mês x minutos de transcrição / 60
B7: Outras tarefas de consolidação (fixas) | C7: =C5-C6 -> 17.4 | D7: h/mês | E7: consolidação informada menos a transcrição
B8: Registro das chamadas em papel | C8: =Parâmetros!$C$5*Parâmetros!$C$6/60 -> 20.4 | D8: h/mês | E8: registros/mês x minutos por chamada / 60
B9: Busca de histórico | C9: =Parâmetros!$C$8*Parâmetros!$C$9/60 -> 8.1666667 | D9: h/mês | E9: consultas/mês x minutos por busca / 60
B10: Prestação de contas trimestral, por mês | C10: =Parâmetros!$C$12*Parâmetros!$C$13/Parâmetros!$C$14 -> 8 | D10: h/mês | E10: 3 dias x 8 h / 3 meses
B11: TOTAL DE HORAS POR MÊS (modelo ajustado) | C11: =C6+C7+C8+C9+C10 -> 84.566667 | D11: h/mês | E11: transcrição + outras + papel + busca + prestação
B12: Custo do tempo operacional | C12: =C11*Parâmetros!$C$15 -> 1564.4833 | D12: R$/mês | E12: horas x custo-hora
B13: Retrabalho, perdas e materiais | C13: =Parâmetros!$C$16+Parâmetros!$C$17+Parâmetros!$C$18 -> 865 | D13: R$/mês | E13: soma dos três componentes do E1.7
B14: CUSTO TOTAL DO PROBLEMA POR MÊS | C14: =C12+C13 -> 2429.4833 | D14: R$/mês | E14: tempo operacional + demais custos
B15: Benefício mensal esperado | C15: =C14*Parâmetros!$C$21 -> 1457.69 | D15: R$/mês | E15: custo do problema x parcela eliminada
B16: Investimento total | C16: =(Parâmetros!$C$22+Parâmetros!$C$23+Parâmetros!$C$24)*Parâmetros!$C$25+Parâmetros!$C$26 -> 22140 | D16: R$ | E16: horas x custo-hora + equipamento
B17: Custo recorrente mensal | C17: =Parâmetros!$C$27+Parâmetros!$C$28*Parâmetros!$C$25+Parâmetros!$C$29 -> 265 | D17: R$/mês | E17: hospedagem + manutenção + energia
B18: Resultado líquido mensal | C18: =C15-C17 -> 1192.69 | D18: R$/mês | E18: benefício menos custo recorrente
B19: Prazo de retorno (payback simples) | C19: =C16/C18 -> 18.56308 | D19: meses | E19: investimento / resultado líquido mensal
B20: Mês em que o fluxo acumulado fica positivo | C20: =ROUNDUP(C19,0) -> 19 | D20: mês | E20: payback arredondado para cima
B21: Resultado acumulado no horizonte | C21: =Parâmetros!$C$30*C18-C16 -> 6484.56 | D21: R$ | E21: meses x líquido menos investimento
B23: COMPARAÇÃO COM O E1.7 ORIGINAL
B24: Horas por mês no E1.7 (soma os 56 h de prestação à transcrição) | C24: =Parâmetros!$C$5*Parâmetros!$C$6/60+Parâmetros!$C$5*Parâmetros!$C$7/60+Parâmetros!$C$8*Parâmetros!$C$9/60+(Parâmetros!$C$10*Parâmetros!$C$11+Parâmetros!$C$12*Parâmetros!$C$13/Parâmetros!$C$14) -> 115.16667 | D24: h/mês
B25: Custo total do problema no E1.7 | C25: =C24*Parâmetros!$C$15+C13 -> 2995.5833 | D25: R$/mês
B26: Payback no E1.7 | C26: =C16/(C25*Parâmetros!$C$21-C17) -> 14.448396 | D26: meses
B27: Horas a menos no modelo ajustado | C27: =C24-C11 -> 30.6 | D27: h/mês
B29: Leitura: o E1.7 soma 30,6 h de transcrição e mais 56 h de "prestação de contas", mas essas 56 h já incluíam as 48 h de transferência de registros relatadas pela coordenação. O ajuste mantém os dois dados observados e conta cada hora uma vez só.

Sheet Derivadas
A1: E2.7 — DERIVADAS APLICADAS AO MODELO DE CUSTO
A2: Modelo: C(R, Q) = w·[ (tp+tt)/60 · R + tb/60 · Q + K ] + O, em que K reúne as horas fixas e O os demais custos.
B4: Derivada | C4: Valor | D4: Unidade | E4: Significado
B5: ∂C/∂R = w·(tp+tt)/60 | C5: =Parâmetros!$C$15*(Parâmetros!$C$6+Parâmetros!$C$7)/60 -> 4.625 | D5: R$ por registro | E5: Cada registro de frequência a mais custa isto por mês em tempo de registro e transcrição.
B6: ∂C/∂Q = w·tb/60 | C6: =Parâmetros!$C$15*Parâmetros!$C$9/60 -> 4.3166667 | D6: R$ por consulta | E6: Cada busca de histórico a mais custa isto por mês.
B7: ∂C/∂w = H | C7: ='Modelo ajustado'!$C$11 -> 84.566667 | D7: horas | E7: Cada R$ 1 a mais no custo-hora aumenta o custo mensal em R$ H.
B8: dR/dt = R·ΔP/P0 | C8: =Parâmetros!$C$5*Parâmetros!$C$20/Parâmetros!$C$19 -> 4.5333333 | D8: registros/mês por mês | E8: Crescimento mensal dos registros no cenário linear (+5 participantes por mês).
B9: dC/dt = (∂C/∂R)·(dR/dt) | C9: =C5*C8 -> 20.966667 | D9: R$/mês por mês | E9: Quanto o custo mensal do problema aumenta a cada mês que passa.
B10: ∂B/∂p = C0 | C10: ='Modelo ajustado'!$C$14 -> 2429.4833 | D10: R$/mês | E10: Benefício mensal por unidade de p (divida por 100 para um ponto percentual).
B11: Valor de 1 ponto percentual de eliminação | C11: =C10/100 -> 24.294833 | D11: R$/mês | E11: Cada 1% do problema eliminado vale isto por mês.
B13: CUSTO DO PROBLEMA AO LONGO DO TEMPO (sem a solução)
B14: Mês t | C14: Registros R(t) | D14: Horas H(t) | E14: Custo C(t) em R$
B15: 0 | C15: =Parâmetros!$C$5+$C$8*B15 -> 204 | D15: =(C15*(Parâmetros!$C$6+Parâmetros!$C$7)/60)+'Modelo ajustado'!$C$9+'Modelo ajustado'!$C$7+'Modelo ajustado'!$C$10 -> 84.566667 | E15: =D15*Parâmetros!$C$15+'Modelo ajustado'!$C$13 -> 2429.4833
B16: 6 | C16: =Parâmetros!$C$5+$C$8*B16 -> 231.2 | D16: =(C16*(Parâmetros!$C$6+Parâmetros!$C$7)/60)+'Modelo ajustado'!$C$9+'Modelo ajustado'!$C$7+'Modelo ajustado'!$C$10 -> 91.366667 | E16: =D16*Parâmetros!$C$15+'Modelo ajustado'!$C$13 -> 2555.2833
B17: 12 | C17: =Parâmetros!$C$5+$C$8*B17 -> 258.4 | D17: =(C17*(Parâmetros!$C$6+Parâmetros!$C$7)/60)+'Modelo ajustado'!$C$9+'Modelo ajustado'!$C$7+'Modelo ajustado'!$C$10 -> 98.166667 | E17: =D17*Parâmetros!$C$15+'Modelo ajustado'!$C$13 -> 2681.0833
B18: 18 | C18: =Parâmetros!$C$5+$C$8*B18 -> 285.6 | D18: =(C18*(Parâmetros!$C$6+Parâmetros!$C$7)/60)+'Modelo ajustado'!$C$9+'Modelo ajustado'!$C$7+'Modelo ajustado'!$C$10 -> 104.96667 | E18: =D18*Parâmetros!$C$15+'Modelo ajustado'!$C$13 -> 2806.8833
B19: 24 | C19: =Parâmetros!$C$5+$C$8*B19 -> 312.8 | D19: =(C19*(Parâmetros!$C$6+Parâmetros!$C$7)/60)+'Modelo ajustado'!$C$9+'Modelo ajustado'!$C$7+'Modelo ajustado'!$C$10 -> 111.76667 | E19: =D19*Parâmetros!$C$15+'Modelo ajustado'!$C$13 -> 2932.6833
B21: Conferência: a diferença entre C(24) e C(0), dividida por 24, é igual a dC/dt (o modelo é linear em t).
B22: Diferença de custo entre mês 24 e mês 0, dividida por 24: | C22: =(E19-E15)/24 -> 20.966667

Sheet Otimização
A1: E2.7 — OTIMIZAÇÃO: QUANTAS HORAS DE DESENVOLVIMENTO MAXIMIZAM O RESULTADO EM 24 MESES
A2: p(h) = pmax·(1 − e^(−h/τ)). NB(h) = T·(B·p(h) − R) − [c·(h + hl + ht) + eq]. Máximo em NB'(h) = 0.
B4: Grandeza | C4: Valor | D4: Unidade | E4: Origem
B5: Eficácia máxima pmax | C5: =Parâmetros!$C$31 -> 0.8 | D5: fração | E5: Parâmetros (premissa)
B6: Eficácia no plano atual p(h0) | C6: =Parâmetros!$C$21 -> 0.6 | D6: fração | E6: E1.7, 60%
B7: Horas do plano atual h0 | C7: =Parâmetros!$C$22 -> 320 | D7: h | E7: E1.7, 320 h
B8: Custo mensal do problema B | C8: ='Modelo ajustado'!$C$14 -> 2429.4833 | D8: R$/mês | E8: Modelo ajustado (constante, sem crescimento: conservador)
B9: Horizonte T | C9: =Parâmetros!$C$30 -> 24 | D9: meses | E9: Parâmetros
B10: Custo da hora c | C10: =Parâmetros!$C$25 -> 45 | D10: R$/h | E10: Parâmetros
B11: Custo recorrente R | C11: ='Modelo ajustado'!$C$17 -> 265 | D11: R$/mês | E11: Modelo ajustado
B12: Custos fixos: c·(hl+ht) + equipamento | C12: =Parâmetros!$C$25*(Parâmetros!$C$23+Parâmetros!$C$24)+Parâmetros!$C$26 -> 7740 | D12: R$ | E12: Parâmetros
B13: Constante τ, calibrada para p(h0) = p0 | C13: =-C7/LN(1-C6/C5) -> 230.83121 | D13: h | E13: τ = −h0 / ln(1 − p0/pmax)
B14: HORAS ÓTIMAS h* | C14: =C13*LN(C9*C8*C5/(C10*C13)) -> 346.70731 | D14: h | E14: h* = τ·ln( T·B·pmax / (c·τ) ), de NB'(h) = 0
B15: Eficácia em h* | C15: =C5*(1-EXP(-C14/C13)) -> 0.62185162 | D15: fração | E15: p(h*)
B16: Resultado em h* (NB) | C16: =C9*(C8*C15-C11)-(C10*C14+C12) -> 6556.8469 | D16: R$ | E16: NB(h*)
B17: Resultado no plano atual, h0 (NB) | C17: =C9*(C8*C6-C11)-(C10*C7+C12) -> 6484.56 | D17: R$ | E17: NB(h0)
B18: Ganho de usar h* em vez de h0 | C18: =C16-C17 -> 72.286941 | D18: R$ | E18: NB(h*) − NB(h0)
B19: Segunda derivada em h* | C19: =-C9*C8*C5/C13^2*EXP(-C14/C13) -> -0.19494764 | D19: R$/h² | E19: NB''(h*) < 0, portanto h* é um máximo
B20: Conferência: NB'(h*) | C20: =C9*C8*C5/C13*EXP(-C14/C13)-C10 -> 0 | D20: R$/h | E20: deve ser zero
B22: CURVA DO RESULTADO
B23: Horas h | C23: p(h) | D23: NB(h) em R$ | E23: NB'(h) em R$/h
B24: 0 | C24: =$C$5*(1-EXP(-B24/$C$13)) -> 0 | D24: =$C$9*($C$8*C24-$C$11)-($C$10*B24+$C$12) -> -14100 | E24: =$C$9*$C$8*$C$5/$C$13*EXP(-B24/$C$13)-$C$10 -> 157.07874
B25: 20 | C25: =$C$5*(1-EXP(-B25/$C$13)) -> 0.066396765 | D25: =$C$9*($C$8*C25-$C$11)-($C$10*B25+$C$12) -> -11128.564 | E25: =$C$9*$C$8*$C$5/$C$13*EXP(-B25/$C$13)-$C$10 -> 140.30702
B26: 40 | C26: =$C$5*(1-EXP(-B26/$C$13)) -> 0.12728287 | D26: =$C$9*($C$8*C26-$C$11)-($C$10*B26+$C$12) -> -8478.4415 | E26: =$C$9*$C$8*$C$5/$C$13*EXP(-B26/$C$13)-$C$10 -> 124.92729
B27: 60 | C27: =$C$5*(1-EXP(-B27/$C$13)) -> 0.18311567 | D27: =$C$9*($C$8*C27-$C$11)-($C$10*B27+$C$12) -> -6122.9648 | E27: =$C$9*$C$8*$C$5/$C$13*EXP(-B27/$C$13)-$C$10 -> 110.82401
B28: 80 | C28: =$C$5*(1-EXP(-B28/$C$13)) -> 0.23431458 | D28: =$C$9*($C$8*C28-$C$11)-($C$10*B28+$C$12) -> -4037.6795 | E28: =$C$9*$C$8*$C$5/$C$13*EXP(-B28/$C$13)-$C$10 -> 97.891249
B29: 100 | C29: =$C$5*(1-EXP(-B29/$C$13)) -> 0.28126418 | D29: =$C$9*($C$8*C29-$C$11)-($C$10*B29+$C$12) -> -2200.1608 | E29: =$C$9*$C$8*$C$5/$C$13*EXP(-B29/$C$13)-$C$10 -> 86.031853
B30: 120 | C30: =$C$5*(1-EXP(-B30/$C$13)) -> 0.32431715 | D30: =$C$9*($C$8*C30-$C$11)-($C$10*B30+$C$12) -> -589.84511 | E30: =$C$9*$C$8*$C$5/$C$13*EXP(-B30/$C$13)-$C$10 -> 75.156739
B31: 140 | C31: =$C$5*(1-EXP(-B31/$C$13)) -> 0.36379691 | D31: =$C$9*($C$8*C31-$C$11)-($C$10*B31+$C$12) -> 812.12453 | E31: =$C$9*$C$8*$C$5/$C$13*EXP(-B31/$C$13)-$C$10 -> 65.184216
B32: 160 | C32: =$C$5*(1-EXP(-B32/$C$13)) -> 0.4 | D32: =$C$9*($C$8*C32-$C$11)-($C$10*B32+$C$12) -> 2023.04 | E32: =$C$9*$C$8*$C$5/$C$13*EXP(-B32/$C$13)-$C$10 -> 56.039371
B33: 180 | C33: =$C$5*(1-EXP(-B33/$C$13)) -> 0.43319838 | D33: =$C$9*($C$8*C33-$C$11)-($C$10*B33+$C$12) -> 3058.758 | E33: =$C$9*$C$8*$C$5/$C$13*EXP(-B33/$C$13)-$C$10 -> 47.653512
B34: 200 | C34: =$C$5*(1-EXP(-B34/$C$13)) -> 0.46364143 | D34: =$C$9*($C$8*C34-$C$11)-($C$10*B34+$C$12) -> 3933.8193 | E34: =$C$9*$C$8*$C$5/$C$13*EXP(-B34/$C$13)-$C$10 -> 39.963645
B35: 220 | C35: =$C$5*(1-EXP(-B35/$C$13)) -> 0.49155783 | D35: =$C$9*($C$8*C35-$C$11)-($C$10*B35+$C$12) -> 4661.5576 | E35: =$C$9*$C$8*$C$5/$C$13*EXP(-B35/$C$13)-$C$10 -> 32.912006
... B64: 800 | C64: =$C$5*(1-EXP(-B64/$C$13)) -> 0.775 | D64: =$C$9*($C$8*C64-$C$11)-($C$10*B64+$C$12) -> -4911.61 | E64: =$C$9*$C$8*$C$5/$C$13*EXP(-B64/$C$13)-$C$10 -> -38.685039

Sheet Sensibilidade
A1: E2.7 — SENSIBILIDADE DA SOLUÇÃO ÓTIMA
A2: A premissa mais frágil é pmax. A tabela mostra o quanto h* e o resultado mudam quando ela muda.
B4: pmax | C4: τ (h) | D4: h* (h) | E4: p(h*) | F4: NB(h*) em R$ | G4: NB(320 h) em R$ | H4: Ganho em R$
B5: 0.65 | C5: =-Parâmetros!$C$22/LN(1-Parâmetros!$C$21/B5) -> 124.7588 | D5: =C5*LN(Parâmetros!$C$30*'Modelo ajustado'!$C$14*B5/(Parâmetros!$C$25*C5)) -> 238.24689 | E5: =B5*(1-EXP(-D5/C5)) -> 0.55371502 | F5: =Parâmetros!$C$30*('Modelo ajustado'!$C$14*E5-'Modelo ajustado'!$C$17)-(Parâmetros!$C$25*D5+Parâmetros!$C$25*(Parâmetros!$C$23+Parâmetros!$C$24)+Parâmetros!$C$26) -> 7464.6838 | G5: =Parâmetros!$C$30*('Modelo ajustado'!$C$14*Parâmetros!$C$21-'Modelo ajustado'!$C$17)-(Parâmetros!$C$25*Parâmetros!$C$22+Parâmetros!$C$25*(Parâmetros!$C$23+Parâmetros!$C$24)+Parâmetros!$C$26) -> 6484.56 | H5: =F5-G5 -> 980.12383
B6: 0.7 | C6: =-Parâmetros!$C$22/LN(1-Parâmetros!$C$21/B6) -> 164.44747 | D6: =C6*LN(Parâmetros!$C$30*'Modelo ajustado'!$C$14*B6/(Parâmetros!$C$25*C6)) -> 280.80377 | E6: =B6*(1-EXP(-D6/C6)) -> 0.57308454 | F6: =Parâmetros!$C$30*('Modelo ajustado'!$C$14*E6-'Modelo ajustado'!$C$17)-(Parâmetros!$C$25*D6+Parâmetros!$C$25*(Parâmetros!$C$23+Parâmetros!$C$24)+Parâmetros!$C$26) -> 6679.014 | G6: =Parâmetros!$C$30*('Modelo ajustado'!$C$14*Parâmetros!$C$21-'Modelo ajustado'!$C$17)-(Parâmetros!$C$25*Parâmetros!$C$22+Parâmetros!$C$25*(Parâmetros!$C$23+Parâmetros!$C$24)+Parâmetros!$C$26) -> 6484.56 | H6: =F6-G6 -> 194.45404
B7: 0.75 | C7: =-Parâmetros!$C$22/LN(1-Parâmetros!$C$21/B7) -> 198.82718 | D7: =C7*LN(Parâmetros!$C$30*'Modelo ajustado'!$C$14*B7/(Parâmetros!$C$25*C7)) -> 315.48051 | E7: =B7*(1-EXP(-D7/C7)) -> 0.59655134 | F7: =Parâmetros!$C$30*('Modelo ajustado'!$C$14*E7-'Modelo ajustado'!$C$17)-(Parâmetros!$C$25*D7+Parâmetros!$C$25*(Parâmetros!$C$23+Parâmetros!$C$24)+Parâmetros!$C$26) -> 6486.854 | G7: =Parâmetros!$C$30*('Modelo ajustado'!$C$14*Parâmetros!$C$21-'Modelo ajustado'!$C$17)-(Parâmetros!$C$25*Parâmetros!$C$22+Parâmetros!$C$25*(Parâmetros!$C$23+Parâmetros!$C$24)+Parâmetros!$C$26) -> 6484.56 | H7: =F7-G7 -> 2.2940425
B8: 0.8 | C8: =-Parâmetros!$C$22/LN(1-Parâmetros!$C$21/B8) -> 230.83121 | D8: =C8*LN(Parâmetros!$C$30*'Modelo ajustado'!$C$14*B8/(Parâmetros!$C$25*C8)) -> 346.70731 | E8: =B8*(1-EXP(-D8/C8)) -> 0.62185162 | F8: =Parâmetros!$C$30*('Modelo ajustado'!$C$14*E8-'Modelo ajustado'!$C$17)-(Parâmetros!$C$25*D8+Parâmetros!$C$25*(Parâmetros!$C$23+Parâmetros!$C$24)+Parâmetros!$C$26) -> 6556.8469 | G8: =Parâmetros!$C$30*('Modelo ajustado'!$C$14*Parâmetros!$C$21-'Modelo ajustado'!$C$17)-(Parâmetros!$C$25*Parâmetros!$C$22+Parâmetros!$C$25*(Parâmetros!$C$23+Parâmetros!$C$24)+Parâmetros!$C$26) -> 6484.56 | H8: =F8-G8 -> 72.286941
B9: 0.85 | C9: =-Parâmetros!$C$22/LN(1-Parâmetros!$C$21/B9) -> 261.48588 | D9: =C9*LN(Parâmetros!$C$30*'Modelo ajustado'!$C$14*B9/(Parâmetros!$C$25*C9)) -> 375.99735 | E9: =B9*(1-EXP(-D9/C9)) -> 0.64819329 | F9: =Parâmetros!$C$30*('Modelo ajustado'!$C$14*E9-'Modelo ajustado'!$C$17)-(Parâmetros!$C$25*D9+Parâmetros!$C$25*(Parâmetros!$C$23+Parâmetros!$C$24)+Parâmetros!$C$26) -> 6774.7144 | G9: =Parâmetros!$C$30*('Modelo ajustado'!$C$14*Parâmetros!$C$21-'Modelo ajustado'!$C$17)-(Parâmetros!$C$25*Parâmetros!$C$22+Parâmetros!$C$25*(Parâmetros!$C$23+Parâmetros!$C$24)+Parâmetros!$C$26) -> 6484.56 | H9: =F9-G9 -> 290.1544
B10: 0.9 | C10: =-Parâmetros!$C$22/LN(1-Parâmetros!$C$21/B10) -> 291.27655 | D10: =C10*LN(Parâmetros!$C$30*'Modelo ajustado'!$C$14*B10/(Parâmetros!$C$25*C10)) -> 404.05637 | E10: =B10*(1-EXP(-D10/C10)) -> 0.67520178 | F10: =Parâmetros!$C$30*('Modelo ajustado'!$C$14*E10-'Modelo ajustado'!$C$17)-(Parâmetros!$C$25*D10+Parâmetros!$C$25*(Parâmetros!$C$23+Parâmetros!$C$24)+Parâmetros!$C$26) -> 7086.8584 | G10: =Parâmetros!$C$30*('Modelo ajustado'!$C$14*Parâmetros!$C$21-'Modelo ajustado'!$C$17)-(Parâmetros!$C$25*Parâmetros!$C$22+Parâmetros!$C$25*(Parâmetros!$C$23+Parâmetros!$C$24)+Parâmetros!$C$26) -> 6484.56 | H10: =F10-G10 -> 602.29837
B11: 0.95 | C11: =-Parâmetros!$C$22/LN(1-Parâmetros!$C$21/B11) -> 320.47147 | D11: =C11*LN(Parâmetros!$C$30*'Modelo ajustado'!$C$14*B11/(Parâmetros!$C$25*C11)) -> 431.27085 | E11: =B11*(1-EXP(-D11/C11)) -> 0.70267005 | F11: =Parâmetros!$C$30*('Modelo ajustado'!$C$14*E11-'Modelo ajustado'!$C$17)-(Parâmetros!$C$25*D11+Parâmetros!$C$25*(Parâmetros!$C$23+Parâmetros!$C$24)+Parâmetros!$C$26) -> 7463.8155 | G11: =Parâmetros!$C$30*('Modelo ajustado'!$C$14*Parâmetros!$C$21-'Modelo ajustado'!$C$17)-(Parâmetros!$C$25*Parâmetros!$C$22+Parâmetros!$C$25*(Parâmetros!$C$23+Parâmetros!$C$24)+Parâmetros!$C$26) -> 6484.56 | H11: =F11-G11 -> 979.25552
B13: Custo do problema B | C13: Variação de B | D13: h* (h) | E13: NB(h*) em R$
B14: ='Modelo ajustado'!$C$14*C14 -> 1943.5867 | C14: 0.8 | D14: =-Parâmetros!$C$22/LN(1-Parâmetros!$C$21/Parâmetros!$C$31)*LN(Parâmetros!$C$30*B14*Parâmetros!$C$31/(Parâmetros!$C$25*(-Parâmetros!$C$22/LN(1-Parâmetros!$C$21/Parâmetros!$C$31)))) -> 295.19881 | E14: =Parâmetros!$C$30*(B14*Parâmetros!$C$31*(1-EXP(-D14/(-Parâmetros!$C$22/LN(1-Parâmetros!$C$21/Parâmetros!$C$31))))-'Modelo ajustado'!$C$17)-(Parâmetros!$C$25*D14+Parâmetros!$C$25*(Parâmetros!$C$23+Parâmetros!$C$24)+Parâmetros!$C$26) -> -454.48678
B15: ='Modelo ajustado'!$C$14*C15 -> 2429.4833 | C15: 1 | D15: =-Parâmetros!$C$22/LN(1-Parâmetros!$C$21/Parâmetros!$C$31)*LN(Parâmetros!$C$30*B15*Parâmetros!$C$31/(Parâmetros!$C$25*(-Parâmetros!$C$22/LN(1-Parâmetros!$C$21/Parâmetros!$C$31)))) -> 346.70731 | E15: =Parâmetros!$C$30*(B15*Parâmetros!$C$31*(1-EXP(-D15/(-Parâmetros!$C$22/LN(1-Parâmetros!$C$21/Parâmetros!$C$31))))-'Modelo ajustado'!$C$17)-(Parâmetros!$C$25*D15+Parâmetros!$C$25*(Parâmetros!$C$23+Parâmetros!$C$24)+Parâmetros!$C$26) -> 6556.8469
B16: ='Modelo ajustado'!$C$14*C16 -> 2915.38 | C16: 1.2 | D16: =-Parâmetros!$C$22/LN(1-Parâmetros!$C$21/Parâmetros!$C$31)*LN(Parâmetros!$C$30*B16*Parâmetros!$C$31/(Parâmetros!$C$25*(-Parâmetros!$C$22/LN(1-Parâmetros!$C$21/Parâmetros!$C$31)))) -> 388.79281 | E16: =Parâmetros!$C$30*(B16*Parâmetros!$C$31*(1-EXP(-D16/(-Parâmetros!$C$22/LN(1-Parâmetros!$C$21/Parâmetros!$C$31))))-'Modelo ajustado'!$C$17)-(Parâmetros!$C$25*D16+Parâmetros!$C$25*(Parâmetros!$C$23+Parâmetros!$C$24)+Parâmetros!$C$26) -> 13992.215
