Workbook

Sheet Instruções
A1: ESTUDO QUANTITATIVO E ECONÔMICO — PLANILHA-MODELO
A2: Projeto Integrador Semestral 2026/2 — Curso de Engenharia de Software — Campus Ceres
B5: COMO USAR ESTA PLANILHA
B6: Preencha somente as células com fundo amarelo e texto em azul. Todas as demais contêm fórmulas e recalculam sozinhas.
B7: Os valores já preenchidos são um EXEMPLO construído com dados plausíveis do Instituto Semear. Substitua-os pelos números levantados pela sua equipe na sessão de descoberta.
B8: Toda premissa adotada deve ser justificada na coluna de observação, indicando a fonte: entrevista, contagem na sessão, documento do caso ou estimativa da equipe.
B10: LEGENDA DE CORES
B11: Texto azul sobre fundo amarelo | C11: valor digitado pela equipe — é aqui que você escreve
B12: Texto preto | C12: fórmula — não altere
B13: Texto verde | C13: valor trazido de outra aba — não altere
B15: ORDEM DE PREENCHIMENTO
B16: 1. Dimensionamento | C16: quantifique o problema como ele é hoje
B17: 2. Projeção | C17: estime como o volume cresce nos próximos 24 meses
B18: 3. Custo do Problema | C18: traduza o problema em dinheiro por mês
B19: 4. Custo da Solução | C19: estime o que custa construir e manter a solução
B20: 5. Fluxo de Caixa | C20: confronte benefício e custo mês a mês
B21: 6. Indicadores | C21: leia o valor presente líquido e o prazo de retorno
B23: ONDE ESTE ESTUDO É COBRADO
B24: Ciclo 1 — entrega em 20/09/2026 | C24: abas 1 e 2 preenchidas (dimensionamento e projeção)
B25: Ciclo 2 — entrega em 25/10/2026 | C25: abas 3 e 4 preenchidas (custo do problema e da solução)
B26: Ciclo 3 — entrega em 29/11/2026 | C26: abas 5 e 6 preenchidas e estudo redigido em linguagem acessível

Sheet 1. Dimensionamento
A1: 1. DIMENSIONAMENTO DO PROBLEMA HOJE
A2: Quantifique a operação atual da organização. Preencha as células amarelas com dados levantados na sessão de descoberta e no dossiê do caso.
B4: Indicador | C4: Valor | D4: Unidade | E4: Fonte / observação
B5: Famílias cadastradas | C5: 140 | D5: famílias | E5: Contagem na planilha CadastroFamilias, e dossiê seção 2
B6: Participantes ativos | C6: 225 | D6: pessoas | E6: Contagem na planilha Participantes, e dossiê seção 2
B7: Oficinas ofertadas por semana | C7: 12 | D7: oficinas | E7: Planilha Oficinas, e dossiê seção 2
B8: Encontros realizados por mês | C8: 48 | D8: encontros | E8: 12 oficinas x 4 semanas (Declaração do Cleber Nunes, E1.2)
B9: Registros de frequência por mês | C9: 204 | D9: registros | E9: Contagem real: 2.239 registros válidos (2.256 linhas - 17 linhas de recado) na planilha Frequencia, cobrindo fev/2025 a dez/2025 (11 meses) = 203,5/mês, arredondado.
B10: Tempo para registrar uma chamada em papel | C10: 6 | D10: minutos | E10: Cronometrado na sessão da semana 4
B11: Tempo para transcrever a chamada para a planilha | C11: 9 | D11: minutos | E11: Cronometrado na sessão
B12: Tempo para localizar um histórico de participante | C12: 14 | D12: minutos | E12: Cronometrado na sessão
B13: Consultas a histórico por mês | C13: 35 | D13: consultas | E13: Estimativa da coordenação
B14: Horas mensais na prestação de contas | C14: 56 | D14: horas | E14: Derivado do Dossiê: "passa três dias somando presença" por trimestre (3 dias x 8h = 24h/trimestre) / 3 = 8h/mês, coexistindo com demias 12h/semana transferindo registros para a planilha (12h x 4 semanas = 48h/mês) registrados pelo relato na Sessão de descoberta (07 e 11/09/2026), Bloco C.4: coordenação
B15: Doações registradas por mês | C15: 4 | D15: registros | E15: Planilha Doacoes, após fazer a média entre as 160 doações válidas na planilha Doacoes, de jan/2024 a dez/2026 (36 meses) = 4,4/mês, arredondado.
B16: Encaminhamentos por mês | C16: 3 | D16: registros | E16: Contagem real: 95 encaminhamentos válidos na planilha Encaminhamentos, de jan/2024 a dez/2026 (33 meses) = 2,9/mês, arredondado.
B18: TEMPO OPERACIONAL CONSUMIDO POR MÊS
B19: Componente | C19: Cálculo | D19: Horas/mês
B20: Registro de chamadas em papel | C20: registros/mês x minutos por chamada / 60 | D20: =C9*C10/60 -> 20.4
B21: Transcrição para a planilha | C21: registros/mês x minutos de transcrição / 60 | D21: =C9*C11/60 -> 30.6
B22: Busca de histórico | C22: consultas/mês x minutos por busca / 60 | D22: =C13*C12/60 -> 8.1666667
B23: Prestação de contas | C23: horas informadas pela coordenação | D23: =C14 -> 56
B24: TOTAL DE HORAS POR MÊS | D24: =SUM(D20:D23) -> 115.16667

Sheet 2. Projeção
A1: 2. PROJEÇÃO DE CRESCIMENTO — 24 MESES
A2: Compare o crescimento linear e o exponencial. Escolha o cenário que a equipe considera realista e justifique a escolha.
B4: Taxa de crescimento mensal (exponencial) | C4: 0.028
B5: Acréscimo mensal absoluto (linear) | C5: 5
B6: Participantes no mês 0 (aba 1) | C6: ='1. Dimensionamento'!C6 -> 225
C7: Cenário adotado pela equipe: Linear. Justificativa: o histórico real de entradas (planilha Participantes, 2023–2026) mostra um ritmo de crescimento de ~55-60 novos participantes/ano após 2024, logo o cenário linear se aplica com maior consistência, ao contrário do exponencial, que seria inconsistente com a capacidade fixa de vagas das 12 oficinas e infraestrutura limitada.
B9: Mês | C9: Participantes (linear) | D9: Participantes (exponencial) | E9: Registros de frequência/mês | F9: Observação
B10: 0 | C10: =$C$6 -> 225 | D10: =$C$6 -> 225 | E10: =D10*'1. Dimensionamento'!$C$9/'1. Dimensionamento'!$C$6 -> 204
B11: 1 | C11: =C10+$C$5 -> 230 | D11: =D10*(1+$C$4) -> 231.3 | E11: =D11*'1. Dimensionamento'!$C$9/'1. Dimensionamento'!$C$6 -> 209.712
B12: 2 | C12: =C11+$C$5 -> 235 | D12: =D11*(1+$C$4) -> 237.7764 | E12: =D12*'1. Dimensionamento'!$C$9/'1. Dimensionamento'!$C$6 -> 215.58394
B13: 3 | C13: =C12+$C$5 -> 240 | D13: =D12*(1+$C$4) -> 244.43414 | E13: =D13*'1. Dimensionamento'!$C$9/'1. Dimensionamento'!$C$6 -> 221.62029
B14: 4 | C14: =C13+$C$5 -> 245 | D14: =D13*(1+$C$4) -> 251.2783 | E14: =D14*'1. Dimensionamento'!$C$9/'1. Dimensionamento'!$C$6 -> 227.82565
B15: 5 | C15: =C14+$C$5 -> 250 | D15: =D14*(1+$C$4) -> 258.31409 | E15: =D15*'1. Dimensionamento'!$C$9/'1. Dimensionamento'!$C$6 -> 234.20477
B16: 6 | C16: =C15+$C$5 -> 255 | D16: =D15*(1+$C$4) -> 265.54688 | E16: =D16*'1. Dimensionamento'!$C$9/'1. Dimensionamento'!$C$6 -> 240.76251
B17: 7 | C17: =C16+$C$5 -> 260 | D17: =D16*(1+$C$4) -> 272.98219 | E17: =D17*'1. Dimensionamento'!$C$9/'1. Dimensionamento'!$C$6 -> 247.50386
B18: 8 | C18: =C17+$C$5 -> 265 | D18: =D17*(1+$C$4) -> 280.6257 | E18: =D18*'1. Dimensionamento'!$C$9/'1. Dimensionamento'!$C$6 -> 254.43396
B19: 9 | C19: =C18+$C$5 -> 270 | D19: =D18*(1+$C$4) -> 288.48322 | E19: =D19*'1. Dimensionamento'!$C$9/'1. Dimensionamento'!$C$6 -> 261.55812
B20: 10 | C20: =C19+$C$5 -> 275 | D20: =D19*(1+$C$4) -> 296.56075 | E20: =D20*'1. Dimensionamento'!$C$9/'1. Dimensionamento'!$C$6 -> 268.88174
B21: 11 | C21: =C20+$C$5 -> 280 | D21: =D20*(1+$C$4) -> 304.86445 | E21: =D21*'1. Dimensionamento'!$C$9/'1. Dimensionamento'!$C$6 -> 276.41043
B22: 12 | C22: =C21+$C$5 -> 285 | D22: =D21*(1+$C$4) -> 313.40065 | E22: =D22*'1. Dimensionamento'!$C$9/'1. Dimensionamento'!$C$6 -> 284.14992
... B34: 24 | C34: =C33+$C$5 -> 345 | D34: =D33*(1+$C$4) -> 436.53319 | E34: =D34*'1. Dimensionamento'!$C$9/'1. Dimensionamento'!$C$6 -> 395.79009

Sheet 3. Custo do Problema
A1: 3. CUSTO MENSAL DO PROBLEMA
A2: Traduza em dinheiro o tempo consumido e as perdas causadas pela forma atual de registro.
B4: Custo-hora médio da equipe da organização | C4: 18.5 | E4: Estimativa a partir do salário informado pela coordenação, com encargos
B5: Horas operacionais consumidas por mês (aba 1) | C5: ='1. Dimensionamento'!D24 -> 115.16667
B7: Componente do custo | C7: Valor mensal | D7: Origem | E7: Observação
B8: Custo do tempo operacional | C8: =C4*C5 -> 2130.5833 | D8: Calculado | E8: Horas x custo-hora
B9: Retrabalho por informação perdida ou duplicada | C9: 320 | D9: Estimado | E9: Justifique a estimativa com base nas evidências do caso
B10: Perdas em prestação de contas e captação | C10: 450 | D10: Estimado | E10: Recursos não obtidos por falta de comprovação
B11: Materiais e impressão de fichas | C11: 95 | D11: Informado | E11: Informado pela organização
B12: CUSTO TOTAL DO PROBLEMA POR MÊS | C12: =SUM(C8:C11) -> 2995.5833
B14: Percentual do problema que a solução elimina | C14: 0.6 | E14: Seja conservador e justifique: nem todo custo desaparece
B15: BENEFÍCIO MENSAL ESPERADO | C15: =C12*C14 -> 1797.35

Sheet 4. Custo da Solução
A1: 4. CUSTO DE CONSTRUÇÃO E DE OPERAÇÃO DA SOLUÇÃO
A2: Estime o esforço de construção e o custo recorrente de manter a solução funcionando.
B4: Item de investimento (uma única vez) | C4: Quantidade | D4: Valor unitário | E4: Total
B5: Horas de desenvolvimento | C5: 320 | D5: 45 | E5: =C5*D5 -> 14400
B6: Horas de levantamento e modelagem | C6: 120 | D6: 45 | E6: =C6*D6 -> 5400
B7: Treinamento da equipe da organização | C7: 12 | D7: 45 | E7: =C7*D7 -> 540
B8: Equipamento e instalação | C8: 1 | D8: 1800 | E8: =C8*D8 -> 1800
B9: INVESTIMENTO TOTAL | E9: =SUM(E5:E8) -> 22140
B11: Custo recorrente (por mês) | C11: Quantidade | D11: Valor unitário | E11: Total
B12: Hospedagem e serviços | C12: 1 | D12: 60 | E12: =C12*D12 -> 60
B13: Manutenção e suporte (horas) | C13: 4 | D13: 45 | E13: =C13*D13 -> 180
B14: Energia e conectividade adicional | C14: 1 | D14: 25 | E14: =C14*D14 -> 25
B15: CUSTO RECORRENTE MENSAL | E15: =SUM(E12:E14) -> 265

Sheet 5. Fluxo de Caixa
A1: 5. FLUXO DE CAIXA — 24 MESES
A2: O mês 0 concentra o investimento. A partir do mês 1, entra o benefício e sai o custo recorrente.
B4: Mês | C4: Benefício | D4: Custo recorrente | E4: Investimento | F4: Fluxo do mês | G4: Fluxo acumulado
B5: 0 | C5: =0 -> 0 | D5: =0 -> 0 | E5: ='4. Custo da Solução'!E9 -> 22140 | F5: =C5-D5-E5 -> -22140 | G5: =F5 -> -22140
B6: 1 | C6: ='3. Custo do Problema'!$C$15 -> 1797.35 | D6: ='4. Custo da Solução'!$E$15 -> 265 | E6: =0 -> 0 | F6: =C6-D6-E6 -> 1532.35 | G6: =G5+F6 -> -20607.65
B7: 2 | C7: ='3. Custo do Problema'!$C$15 -> 1797.35 | D7: ='4. Custo da Solução'!$E$15 -> 265 | E7: =0 -> 0 | F7: =C7-D7-E7 -> 1532.35 | G7: =G6+F7 -> -19075.3
B8: 3 | C8: ='3. Custo do Problema'!$C$15 -> 1797.35 | D8: ='4. Custo da Solução'!$E$15 -> 265 | E8: =0 -> 0 | F8: =C8-D8-E8 -> 1532.35 | G8: =G7+F8 -> -17542.95
B9: 4 | C9: ='3. Custo do Problema'!$C$15 -> 1797.35 | D9: ='4. Custo da Solução'!$E$15 -> 265 | E9: =0 -> 0 | F9: =C9-D9-E9 -> 1532.35 | G9: =G8+F9 -> -16010.6
B10: 5 | C10: ='3. Custo do Problema'!$C$15 -> 1797.35 | D10: ='4. Custo da Solução'!$E$15 -> 265 | E10: =0 -> 0 | F10: =C10-D10-E10 -> 1532.35 | G10: =G9+F10 -> -14478.25
B11: 6 | C11: ='3. Custo do Problema'!$C$15 -> 1797.35 | D11: ='4. Custo da Solução'!$E$15 -> 265 | E11: =0 -> 0 | F11: =C11-D11-E11 -> 1532.35 | G11: =G10+F11 -> -12945.9
B12: 7 | C12: ='3. Custo do Problema'!$C$15 -> 1797.35 | D12: ='4. Custo da Solução'!$E$15 -> 265 | E12: =0 -> 0 | F12: =C12-D12-E12 -> 1532.35 | G12: =G11+F12 -> -11413.55
B13: 8 | C13: ='3. Custo do Problema'!$C$15 -> 1797.35 | D13: ='4. Custo da Solução'!$E$15 -> 265 | E13: =0 -> 0 | F13: =C13-D13-E13 -> 1532.35 | G13: =G12+F13 -> -9881.2
B14: 9 | C14: ='3. Custo do Problema'!$C$15 -> 1797.35 | D14: ='4. Custo da Solução'!$E$15 -> 265 | E14: =0 -> 0 | F14: =C14-D14-E14 -> 1532.35 | G14: =G13+F14 -> -8348.85
B15: 10 | C15: ='3. Custo do Problema'!$C$15 -> 1797.35 | D15: ='4. Custo da Solução'!$E$15 -> 265 | E15: =0 -> 0 | F15: =C15-D15-E15 -> 1532.35 | G15: =G14+F15 -> -6816.5
B16: 11 | C16: ='3. Custo do Problema'!$C$15 -> 1797.35 | D16: ='4. Custo da Solução'!$E$15 -> 265 | E16: =0 -> 0 | F16: =C16-D16-E16 -> 1532.35 | G16: =G15+F16 -> -5284.15
B17: 12 | C17: ='3. Custo do Problema'!$C$15 -> 1797.35 | D17: ='4. Custo da Solução'!$E$15 -> 265 | E17: =0 -> 0 | F17: =C17-D17-E17 -> 1532.35 | G17: =G16+F17 -> -3751.8
... B29: 24 | C29: ='3. Custo do Problema'!$C$15 -> 1797.35 | D29: ='4. Custo da Solução'!$E$15 -> 265 | E29: =0 -> 0 | F29: =C29-D29-E29 -> 1532.35 | G29: =G28+F29 -> 14636.4

Sheet 6. Indicadores
A1: 6. INDICADORES DE VIABILIDADE
A2: Leitura final do estudo. Estes números devem ser explicados em linguagem acessível na devolutiva à organização.
B4: Taxa de desconto mensal | C4: 0.008 | D4: Custo de oportunidade mensal adotado pela equipe — justifique a escolha
B6: Valor presente líquido (VPL) em 24 meses | C6: {=NPV(C4,'5. Fluxo de Caixa'!F6:F29)+'5. Fluxo de Caixa'!F5} -> 11200.568 | D6: Positivo indica que a solução se paga dentro do horizonte analisado
B7: Taxa interna de retorno mensal (TIR) | C7: =IFERROR(IRR('5. Fluxo de Caixa'!F5:F29),"não aplicável") -> 0.045326257 | D7: Compare com a taxa de desconto adotada
B8: Prazo de retorno (payback simples, em meses) | C8: {=IFERROR(MATCH(TRUE,INDEX('5. Fluxo de Caixa'!G5:G29>0,0),0)-1,"não retorna em 24 meses")} -> 15 | D8: Mês em que o fluxo acumulado passa a ser positivo
B9: Benefício acumulado em 24 meses | C9: ='5. Fluxo de Caixa'!G29 -> 14636.4 | D9: Resultado acumulado ao final do horizonte
B11: LEITURA DO RESULTADO
B12: Escreva aqui, em no máximo cinco linhas e sem jargão técnico, o que estes números significam para o Instituto Semear: ____________________________________________
